oasys2/__init__.py
oasys2/canvas/__init__.py
oasys2/canvas/__main__.py
oasys2/canvas/config.py
oasys2/canvas/application/__init__.py
oasys2/canvas/application/addons.py
oasys2/canvas/application/canvasmain.py
oasys2/canvas/application/internal_libraries.py
oasys2/canvas/application/data/INTERNAL_LIBRARIES.txt
oasys2/canvas/application/data/OFFICIAL_ADDONS.txt
oasys2/canvas/icons/Install.svg
oasys2/canvas/icons/Oasys.svg
oasys2/canvas/icons/oasys-splash-screen.png
oasys2/canvas/icons/oasys.png
oasys2/canvas/menus/__init__.py
oasys2/canvas/menus/menu.py
oasys2/canvas/registry/__init__.py
oasys2/canvas/registry/discovery.py
oasys2/canvas/scheme/__init__.py
oasys2/canvas/scheme/readwrite.py
oasys2/canvas/scheme/data/oasys1-to-oasys2.json
oasys2/canvas/util/__init__.py
oasys2/canvas/util/canvas_util.py
oasys2/canvas/util/external_command.py
oasys2/widget/__init__.py
oasys2/widget/gui.py
oasys2/widget/widget.py
oasys2/widget/util/__init__.py
oasys2/widget/util/congruence.py
oasys2/widget/util/exchange.py
oasys2/widget/util/scanning.py
oasys2/widget/util/widget_objects.py
oasys2/widget/util/widget_util.py
oasys2/widget/util/script/__init__.py
oasys2/widget/util/script/itemmodels.py
oasys2/widget/util/script/value.py
oasys2/widget/util/script/variable.py
oasys2/widget/workflow/__init__.py
oasys2/widget/workflow/widgetsscheme.py
oasys2/widgets/__init__.py
oasys2/widgets/abstract/__init__.py
oasys2/widgets/abstract/scanning/__init__.py
oasys2/widgets/abstract/scanning/abstract_scan_file_node_point.py
oasys2/widgets/abstract/scanning/abstract_scan_node_point.py
oasys2/widgets/abstract/scanning/abstract_scan_variable_node_point.py
oasys2/widgets/loops/__init__.py
oasys2/widgets/loops/ow_node_point.py
oasys2/widgets/loops/ow_pin.py
oasys2/widgets/loops/ow_scan_file_node_point.py
oasys2/widgets/loops/ow_scan_variable_node_point.py
oasys2/widgets/loops/icons/cycle.png
oasys2/widgets/loops/icons/cycle_file.png
oasys2/widgets/loops/icons/cycle_variable.png
oasys2-0.0.38.dist-info/licenses/LICENSE.txt
oasys2-0.0.38.dist-info/METADATA
oasys2-0.0.38.dist-info/WHEEL
oasys2-0.0.38.dist-info/entry_points.txt
oasys2-0.0.38.dist-info/top_level.txt
oasys2-0.0.38.dist-info/RECORD
